science_mode_4/__init__.py
science_mode_4/device.py
science_mode_4/device_i24.py
science_mode_4/device_p24.py
science_mode_4/layer.py
science_mode_4/requirements.txt
science_mode_4/dyscom/__init__.py
science_mode_4/dyscom/dyscom_get.py
science_mode_4/dyscom/dyscom_get_battery_status.py
science_mode_4/dyscom/dyscom_get_device_id.py
science_mode_4/dyscom/dyscom_get_file_by_name.py
science_mode_4/dyscom/dyscom_get_file_info.py
science_mode_4/dyscom/dyscom_get_file_system_status.py
science_mode_4/dyscom/dyscom_get_firmware_version.py
science_mode_4/dyscom/dyscom_get_list_of_measurement_meta_info.py
science_mode_4/dyscom/dyscom_get_operation_mode.py
science_mode_4/dyscom/dyscom_helper.py
science_mode_4/dyscom/dyscom_init.py
science_mode_4/dyscom/dyscom_layer.py
science_mode_4/dyscom/dyscom_power_module.py
science_mode_4/dyscom/dyscom_send_file.py
science_mode_4/dyscom/dyscom_send_live_data.py
science_mode_4/dyscom/dyscom_send_measurement_meta_info.py
science_mode_4/dyscom/dyscom_start.py
science_mode_4/dyscom/dyscom_stop.py
science_mode_4/dyscom/dyscom_sys.py
science_mode_4/dyscom/dyscom_types.py
science_mode_4/dyscom/ads129x/__init__.py
science_mode_4/dyscom/ads129x/ads129x.py
science_mode_4/dyscom/ads129x/ads129x_channel_settings_register.py
science_mode_4/dyscom/ads129x/ads129x_config_register_1.py
science_mode_4/dyscom/ads129x/ads129x_config_register_2.py
science_mode_4/dyscom/ads129x/ads129x_config_register_3.py
science_mode_4/dyscom/ads129x/ads129x_config_register_4.py
science_mode_4/dyscom/ads129x/ads129x_respiration_control_register.py
science_mode_4/general/__init__.py
science_mode_4/general/general_device_id.py
science_mode_4/general/general_error.py
science_mode_4/general/general_layer.py
science_mode_4/general/general_reset.py
science_mode_4/general/general_stim_status.py
science_mode_4/general/general_types.py
science_mode_4/general/general_unknown_command.py
science_mode_4/general/general_version.py
science_mode_4/low_level/__init__.py
science_mode_4-0.0.20.dist-info/METADATA
science_mode_4-0.0.20.dist-info/WHEEL
science_mode_4-0.0.20.dist-info/licenses/LICENSE
science_mode_4-0.0.20.dist-info/RECORD
