Metadata-Version: 2.4
Name: science_mode_4
Version: 0.0.20
Summary: Native ScienceMode4 protocol implementation
Project-URL: Homepage, https://github.com/nextroundwinner/ScienceModePython
Author-email: Marc Hofmann <marc-hofmann@gmx.de>
License-Expression: MIT
License-File: LICENSE
Classifier: Operating System :: OS Independent
Classifier: Programming Language :: Python :: 3
Requires-Python: >=3.11
Requires-Dist: libusb-package
Requires-Dist: pyserial
Requires-Dist: pyusb
